jekyllmarkdown/__init__.py
jekyllmarkdown/templates/jekyllmarkdown.tpl
jekyllmarkdown-0.1.dist-info/LICENSE
jekyllmarkdown-0.1.dist-info/WHEEL
jekyllmarkdown-0.1.dist-info/METADATA
jekyllmarkdown-0.1.dist-info/RECORD
